{"name":"Giftlist","tagline":"Eine Geschenkliste / a Presentlist / ein Wunschzettel","body":"# Presentlist / Geschenkeliste #\r\n\r\n=> !! For English => english is under german !!\r\n\r\nPresentlist ist eine Geschenkliste auf der man seine Wünsche zur Hochzeit, Geburtstag oder anderen Anlässen auflisten kann. Dabei kann man einen Titel, Beschreibung und auch ein Bild zum Geschnenk angeben, sowie Links zu Händlern oder dem Produkt angeben. Wenn sich dann jemand ein Geschenk von der Liste nimmt, ist es für die anderen nicht mehr sichtbar. Man kann gewählte Geschenke aber auch wieder freigeben und der Administrator sieht nicht wer sich welches Geschenk genommen hat. \r\n\r\n![](https://raw2.github.com/lightszentip/giftlist/gh-pages/screenshot01.PNG)\r\n![](https://raw2.github.com/lightszentip/giftlist/gh-pages/screenshot03.PNG)\r\n![](https://raw2.github.com/lightszentip/giftlist/gh-pages/screenshot04.PNG)\r\n\r\n## Funktionen ##\r\n- Install Wizard\r\n- Geschenkeliste\r\n- Detail Ansicht von Geschenken\r\n- Geschenk auswählen\r\n- Geschenk freigeben\r\n- Geschenk per Mail teilen\r\n- Backend\r\n\t- Geschenk anlegen / editieren / löschen\r\n\t- Benutzer anlegen\r\n\t- Profil editieren\r\n\t- Passwort vergessen\r\n\t- Login / Logout\r\n\t- Wartungsmodus aktivieren\r\n\t- Einstellungen ändern\r\n\r\n\r\n## Requirements ##\r\n\r\n- PHP 5.3.7 oder höher\r\n- MySQL Datenbank (andere sind aktuell nur durch bearbeiten der Sources möglich)\r\n- PHP PDO Support für MySQL aktiv (extension=php_pdo_mysql.dll)\r\n\r\n\r\n## Anleitung ##\r\n\r\nDie Zip Datei im gewüschten Ordner entpacken und die Url zum Ordner aufrufen. Danach wird man auf den Install Wizard weitergeleitet. Nach dem ausführen des Install Wizard den setup Ordner löschen. Danach sich anmelden und das Passwort und die Email Adresse des Admin Benutzers ändern. Durch das Ändern des Benutzernamens wird zudem die Sicherheit erhöht.\r\n\r\nBei Fragen/Problemen/Erweiterungen und Feedback stehe ich gerne zur Verfügung. Entweder per Email oder durch erstellen eines Issues.\r\n\r\n## English ##\r\n\r\nThe app presentlist is show the wishes from wedding, birthday or from other occasions. You can create a present with a title, description, image and links. If a user take a present from the list, it is not visible for other user.\r\n\r\n\r\n\r\n## Functions ##\r\n- Install Wizard\r\n- list with presents\r\n- detail view of present\r\n- use a present\r\n- release a gift\r\n- Backend\r\n\t- create, edit, delete a present\r\n\t- create user\r\n\t- edit profile\r\n\t- forgotten password\r\n\t- Login / Logout\r\n\t- maintenance mode\r\n\t- change settings\r\n\r\n\r\n## Requirements ##\r\n\r\n- PHP 5.3.7 or higher\r\n- MySQL Database (other database only support by you edit the source files)\r\n- PHP PDO Support for MySQL active (extension=php_pdo_mysql.dll)\r\n\r\n\r\n## Instructions ##\r\n\r\nUnpack the zip file to the target dir and open the url in your browser. Follow the steps of install wizard. Delete the setup folder and change the password and email address of  admin account.\r\n\r\nIf you have a question, problems or feedback then you can send a mail or create a new issue.\r\n\r\n## Verwendete PHP Libraries / Used lbraries: ##\r\n\r\n- Rain TPL => [https://github.com/rainphp/raintpl](https://github.com/rainphp/raintpl)\r\n- php-i18n von Philipp Schröer=> [https://github.com/Philipp15b/php-i18n?files=1](https://github.com/Philipp15b/php-i18n?files=1)\r\n- Medoo DB => [http://medoo.in/api/new](http://medoo.in/api/new)\r\n- PHP Setup / Installer Script => [http://www.effiziente-webprogrammierung.info/php-scripts/setup-wizard-installer](http://www.effiziente-webprogrammierung.info/php-scripts/setup-wizard-installer)\r\n- PHP Login von http://www.php-login.net/ => [https://github.com/panique/php-login](https://github.com/panique/php-login) -> Version Advanced\r\n\r\n## Verwendete JS/HTML/CSS Komponeneten / Used JS/HTML/CSS components: ##\r\n\r\n- TableSorter von Christian Bach => [http://mottie.github.io/tablesorter/](https://github.com/Mottie/tablesorter)\r\n- Bootstrap 3.1 => [http://getbootstrap.com/](http://getbootstrap.com/)","google":"","note":"Don't delete this file! It's used internally to help with page regeneration."}